azure/storage/__init__.py
azure/storage/_auth.py
azure/storage/_common_conversion.py
azure/storage/_connection.py
azure/storage/_constants.py
azure/storage/_deserialization.py
azure/storage/_encryption.py
azure/storage/_error.py
azure/storage/_serialization.py
azure/storage/cloudstorageaccount.py
azure/storage/models.py
azure/storage/retry.py
azure/storage/sharedaccesssignature.py
azure/storage/storageclient.py
azure/storage/_http/__init__.py
azure/storage/_http/batchclient.py
azure/storage/_http/httpclient.py
azure/storage/blob/__init__.py
azure/storage/blob/_deserialization.py
azure/storage/blob/_download_chunking.py
azure/storage/blob/_encryption.py
azure/storage/blob/_error.py
azure/storage/blob/_serialization.py
azure/storage/blob/_upload_chunking.py
azure/storage/blob/appendblobservice.py
azure/storage/blob/baseblobservice.py
azure/storage/blob/blockblobservice.py
azure/storage/blob/models.py
azure/storage/blob/pageblobservice.py
azure/storage/file/__init__.py
azure/storage/file/_deserialization.py
azure/storage/file/_download_chunking.py
azure/storage/file/_serialization.py
azure/storage/file/_upload_chunking.py
azure/storage/file/fileservice.py
azure/storage/file/models.py
azure/storage/queue/__init__.py
azure/storage/queue/_deserialization.py
azure/storage/queue/_encryption.py
azure/storage/queue/_error.py
azure/storage/queue/_serialization.py
azure/storage/queue/models.py
azure/storage/queue/queueservice.py
azure/storage/table/__init__.py
azure/storage/table/_deserialization.py
azure/storage/table/_encryption.py
azure/storage/table/_error.py
azure/storage/table/_request.py
azure/storage/table/_serialization.py
azure/storage/table/models.py
azure/storage/table/tablebatch.py
azure/storage/table/tableservice.py
azure_storage-0.36.0.dist-info/DESCRIPTION.rst
azure_storage-0.36.0.dist-info/METADATA
azure_storage-0.36.0.dist-info/RECORD
azure_storage-0.36.0.dist-info/WHEEL
azure_storage-0.36.0.dist-info/metadata.json
azure_storage-0.36.0.dist-info/top_level.txt
