Metadata-Version: 1.1
Name: azure-storage
Version: 0.36.0
Summary: Microsoft Azure Storage Client Library for Python
Home-page: https://github.com/Azure/azure-storage-python
Author: Microsoft Corporation
Author-email: ptvshelp@microsoft.com
License: Apache License 2.0
Platform: UNKNOWN
Classifier: Development Status :: 4 - Beta
Classifier: Programming Language :: Python
Classifier: Programming Language :: Python :: 2
Classifier: Programming Language :: Python :: 2.7
Classifier: Programming Language :: Python :: 3
Classifier: Programming Language :: Python :: 3.3
Classifier: Programming Language :: Python :: 3.4
Classifier: Programming Language :: Python :: 3.5
Classifier: License :: OSI Approved :: Apache Software License
